ihackit/__init__.py
ihackit/constant.py
ihackit/device.py
ihackit/facebook.py
ihackit/generator.py
ihackit/headers.py
ihackit/identifier.py
ihackit/instagram.py
ihackit/useragent.py
ihackit-0.0.2.dist-info/licenses/LICENSE
ihackit-0.0.2.dist-info/METADATA
ihackit-0.0.2.dist-info/WHEEL
ihackit-0.0.2.dist-info/top_level.txt
ihackit-0.0.2.dist-info/RECORD
