Metadata-Version: 2.4
Name: ihackit
Version: 0.0.2
Summary: Instagram Automation, Device Customization & User-Agent Generator Library
Home-page: https://pypi.org/project/ihackit
Author: Moh Iqbal Hidayat
Author-email: Moh Iqbal Hidayat <iqbalmh18.dev@gmail.com>
License: MIT License
Project-URL: Homepage, https://pypi.org/project/ihackit
Project-URL: Source, https://github.com/iqbalmh18/ihackit
Keywords: ihackit,instagram,instagram-api,instagram-bot,instagram-private-api
Classifier: Programming Language :: Python :: 3
Classifier: License :: OSI Approved :: MIT License
Classifier: Operating System :: OS Independent
Requires-Python: >=3.7
License-File: LICENSE
Requires-Dist: requests
Requires-Dist: pycryptodomex
Dynamic: author
Dynamic: home-page
Dynamic: license-file
Dynamic: requires-python
